netbox_notices-0.2.3.dist-info/licenses/LICENSE
notices/__init__.py
notices/choices.py
notices/constants.py
notices/filtersets.py
notices/forms.py
notices/ical_utils.py
notices/models.py
notices/navigation.py
notices/signals.py
notices/tables.py
notices/template_content.py
notices/timeline_utils.py
notices/urls.py
notices/utils.py
notices/views.py
notices/widgets.py
notices/api/__init__.py
notices/api/serializers.py
notices/api/urls.py
notices/api/views.py
notices/migrations/0001_initial.py
notices/migrations/0002_maintenance_impact_outage_impact.py
notices/migrations/0003_alter_outage_start.py
notices/migrations/0004_outage_reported_at.py
notices/migrations/__init__.py
notices/static/notices/css/calendar-overrides.css
notices/static/notices/css/fullcalendar/index.min.css
notices/static/notices/js/calendar.js
notices/static/notices/js/fullcalendar/LICENSE.txt
notices/static/notices/js/fullcalendar/index.global.min.js
notices/templates/notices/calendar.html
notices/templates/notices/calendar_widget.html
notices/templates/notices/event_history_table.html
notices/templates/notices/event_history_tabs.html
notices/templates/notices/eventnotification.html
notices/templates/notices/maintenance.html
notices/templates/notices/maintenance_cancel.html
notices/templates/notices/maintenance_include.html
notices/templates/notices/maintenance_reschedule.html
notices/templates/notices/outage.html
notices/templates/notices/provider_include.html
notices/templates/notices/widget.html
netbox_notices-0.2.3.dist-info/METADATA
netbox_notices-0.2.3.dist-info/WHEEL
netbox_notices-0.2.3.dist-info/top_level.txt
netbox_notices-0.2.3.dist-info/RECORD
