Metadata-Version: 2.4
Name: netbox-notices
Version: 0.2.3
Summary: Track maintenance and outage events across various NetBox models from vendors and internal sources.
Author-email: Jonathan Senecal <contact@jonathansenecal.com>, Jason Yates <me@jasonyates.co.uk>
Project-URL: Homepage, https://github.com/jsenecal/netbox-notices
Project-URL: Documentation, https://jsenecal.github.io/netbox-notices
Project-URL: Source, https://github.com/jsenecal/netbox-notices
Project-URL: Tracker, https://github.com/jsenecal/netbox-notices/issues
Keywords: notices
Classifier: Development Status :: 2 - Pre-Alpha
Classifier: Intended Audience :: Developers
Classifier: Natural Language :: English
Classifier: Programming Language :: Python :: 3
Classifier: Programming Language :: Python :: 3.10
Classifier: Programming Language :: Python :: 3.11
Classifier: Programming Language :: Python :: 3.12
Requires-Python: >=3.10.0
License-File: LICENSE
Requires-Dist: icalendar>=5.0.0
Provides-Extra: dev
Requires-Dist: black==25.1.0; extra == "dev"
Requires-Dist: bumpver; extra == "dev"
Requires-Dist: isort==6.0.1; extra == "dev"
Requires-Dist: pip-tools; extra == "dev"
Requires-Dist: pre-commit>=4.0.0; extra == "dev"
Requires-Dist: pytest; extra == "dev"
Requires-Dist: pytest-django>=4.5.0; extra == "dev"
Requires-Dist: pytest-cov>=3.0.0; extra == "dev"
Requires-Dist: flake8>=7.0.0; extra == "dev"
Requires-Dist: pyproject-flake8>=7.0.0; extra == "dev"
Requires-Dist: twine==6.1.0; extra == "dev"
Requires-Dist: Sphinx==8.2.3; extra == "dev"
Requires-Dist: watchdog==6.0.0; extra == "dev"
Dynamic: license-file
